{
  "Ver_Vermillion": {
    "id": "2060458054416548316",
    "created_at": "Fri May 29 20:27:36 +0000 2026",
    "full_text": "【MARIO KART WORLD】 WITH VIEWERS!  🫵🫵🫵\n\nNow's your chance to leave me in the dust :3 \n\nhttps://t.co/j0CdqTQL51 via @YouTube \n\n#NIJI_ENRoute https://t.co/R215cJsxEp",
    "img": "https://pbs.twimg.com/media/HJg3hRZXMAEmkh0.jpg",
    "height": 675,
    "width": 1200,
    "type": "photo"
  },
  "Tyrant_Vanta": {
    "id": "2060656558225375262",
    "created_at": "Sat May 30 09:36:23 +0000 2026",
    "full_text": "🃏WEEKLY SCHEDULE🔪\nSchedule for the week of May 25th!\n\nLate schedule Teehee. Sorry my life is such a mess right now https://t.co/0gqzhhlTIO",
    "img": "https://pbs.twimg.com/media/HJjsN_XbcAAdQCO.jpg",
    "height": 780,
    "width": 1200,
    "type": "photo"
  },
  "Alban_Knox": {
    "id": "2061262452130456055",
    "created_at": "Mon Jun 01 01:43:59 +0000 2026",
    "full_text": "We finally have a new schedule!! Mario Kart week, vroom vroom 🏎️🌪️\n\n🐱🧡\n\nGeneral: #AlbanKnox\nLive: #AlbanLive\nArt: #AlbanKnoxArt\nNSFW: #KnoxSFW\nMeme: #DeezKnox\nThumbnail &amp; Assets: #AlbanGraphics\nClips: #KnoxClips https://t.co/pEDarSp3uE",
    "img": "https://pbs.twimg.com/media/HJsTMhDWcAkncLC.jpg",
    "height": 675,
    "width": 1200,
    "type": "photo"
  },
  "uki_violeta": {
    "id": "2061510497602797625",
    "created_at": "Mon Jun 01 18:09:38 +0000 2026",
    "full_text": "【🔮 Weekly Schedule! 🌌】\nJun 01 - Jun 07\n\nGeneral #UkiVioleta\nLive #UkiLive\nArt #VioletAtelier\nAssets #VioletAssets\nMeme #uwukiVioleta\nNSFW #UKinky\nThumbnails #UkiThumb\nClips #Ukilipse\n🍳 #Violeggta\nCute #fuwauki\nDrinks #violatte\nCos #ukiform\nFan Name / Stargazers\n\n#NOCTYX\n(all https://t.co/SEnP15bTUN",
    "img": "https://pbs.twimg.com/media/HJv03p2aMAAYHca.jpg",
    "height": 675,
    "width": 1200,
    "type": "photo"
  },
  "AiaAmare": {
    "id": "2061522838503239710",
    "created_at": "Mon Jun 01 18:58:40 +0000 2026",
    "full_text": "WEEKLY SCHEDULE【6/1-6/7】\n(updated schedule to swap a stream!) \n👼⭐️\nTAGS:\n✰ GENERAL: #AiaAmare\n✰ LIVE: #AiaAmareLIVE \n✰ ART: #AmareAtelier \n✰ ASSETS: #AiaAssets\n✰ CLIPS: #AiaClips\n✰ NSFW: #AmarErotic\n✰ RANDOM: #DearDAiary\n✰ MEME: #AIYAHamare\n✰ FANS: #Aiadmirers https://t.co/l7WVcR2cUJ",
    "img": "https://pbs.twimg.com/media/HJwAB5mXYAA7Xcj.jpg",
    "height": 675,
    "width": 1200,
    "type": "photo"
  },
  "ScarleYonaguni": {
    "id": "2061525722100080962",
    "created_at": "Mon Jun 01 19:10:08 +0000 2026",
    "full_text": "🚬💔COVER ANNOUNCEMENT💔🚬\n\n酔いどれ知らず/ Yoidore Shirazu ver. Scarle Yonaguni\n\n🗓️: Saturday June 6, 2026\n🕔: 4pm PST | 7pm EST | 9am JST\n\nCome join me at the Premiere!🎤💔\n⏬Youtube Premiere⏬:\nhttps://t.co/oZ1D0BGztV https://t.co/zouNfMLl0e",
    "img": "https://pbs.twimg.com/media/HJwCuAlakAAOevc.jpg",
    "height": 675,
    "width": 1200,
    "type": "photo"
  }
}