{
  "Ver_Vermillion": {
    "id": "2045288241872388495",
    "created_at": "Fri Apr 17 23:48:11 +0000 2026",
    "full_text": "【POKÉMON LEGENDS: Z-A】 while everyone is playing tomodachi life, my life is back in POKÉMON !!! \n\n🕤 9:30 AM EST | 10:30 PM JST\n\n🔗: https://t.co/dTuliewnhr https://t.co/AUIQLPSHUS",
    "img": "https://pbs.twimg.com/media/HGJSjaeWMAAQg1i.jpg",
    "height": 675,
    "width": 1200,
    "type": "photo"
  },
  "EnnaAlouette": {
    "id": "2045715074292043816",
    "created_at": "Sun Apr 19 04:04:15 +0000 2026",
    "full_text": "【Tomodachi Life: Living the Dream】\nsorry guys i rly couldn't wait anymore I REALLY WANNA PLAY TOMODACHI LIFE so i'm playing it....in 9hrs LOL it's the start of a new world !!! ✨✨✨\n\nWaiting Room:\n04.19 - 10AM EDT / 7AM PDT / 4PM CEST / 11PM JST\nhttps://t.co/mzJ9nLSK9c https://t.co/Xh7qMi9YVD",
    "img": "https://pbs.twimg.com/media/HGPW059WgAA1l9n.jpg",
    "height": 675,
    "width": 1200,
    "type": "photo"
  }
}